abha_devservice_apis/__init__.py
abha_devservice_apis/apis.py
abha_devservice_apis-0.1.0.dist-info/METADATA
abha_devservice_apis-0.1.0.dist-info/WHEEL
abha_devservice_apis-0.1.0.dist-info/RECORD
