Metadata-Version: 2.1
Name: abha-devservice-apis
Version: 0.1.0
Summary: 
Author: Aditya-Kumar-Code
Author-email: 87271653+Aditya-Kumar-Code@users.noreply.github.com
Requires-Python: >=3.12,<4.0
Classifier: Programming Language :: Python :: 3
Classifier: Programming Language :: Python :: 3.12
Requires-Dist: requests (>=2.31.0,<3.0.0)
